isage_flow-0.1.2.dist-info/licenses/LICENSE
sage_flow/CMakeLists.txt
sage_flow/__init__.py
sage_flow/_sage_flow.cpython-311-x86_64-linux-gnu.so
sage_flow/_version.py
sage_flow/bindings.cpp
sage_flow/libsageflow.so
isage_flow-0.1.2.dist-info/METADATA
isage_flow-0.1.2.dist-info/WHEEL
isage_flow-0.1.2.dist-info/RECORD
