Metadata-Version: 2.2
Name: isage-flow
Version: 0.1.2
Summary: SageFlow - Vector-native stream processing engine for incremental semantic state snapshots
Author-Email: IntelliStream Team <shuhao_zhang@hust.edu.cn>
License: Apache-2.0
Classifier: Development Status :: 3 - Alpha
Classifier: Intended Audience :: Developers
Classifier: License :: OSI Approved :: Apache Software License
Classifier: Programming Language :: Python :: 3
Classifier: Programming Language :: Python :: 3.10
Classifier: Programming Language :: Python :: 3.11
Classifier: Programming Language :: C++
Classifier: Topic :: Software Development :: Libraries :: Python Modules
Project-URL: Homepage, https://github.com/intellistream/sageFlow
Project-URL: Documentation, https://intellistream.github.io/SAGE/
Project-URL: Repository, https://github.com/intellistream/sageFlow
Requires-Python: >=3.10
Requires-Dist: numpy<2.3.0,>=1.26.0
Provides-Extra: dev
Requires-Dist: pytest>=7.0.0; extra == "dev"
Requires-Dist: pytest-cov>=4.0.0; extra == "dev"
